{
  "name": "Ergopti",
  "description": "Disposition ergonomique optimisée pour le français, l’anglais et le code",
  "geometry": "ergo",
  "keymap": {
    "Digit1": [ "1", "1", "₁", "¹" ],
    "Digit2": [ "2", "2", "₂", "²" ],
    "Digit3": [ "3", "3", "₃", "³" ],
    "Digit4": [ "4", "4", "₄", "⁴" ],
    "Digit5": [ "5", "5", "₅", "⁵" ],
    "Digit6": [ "6", "6", "₆", "⁶" ],
    "Digit7": [ "7", "7", "₇", "⁷" ],
    "Digit8": [ "8", "8", "₈", "⁸" ],
    "Digit9": [ "9", "9", "₉", "⁹" ],
    "Digit0": [ "0", "º", "₀", "⁰" ],
    "KeyQ": [ "z", "Z", "`", "„" ],
    "KeyW": [ "y", "Y", "@", "„" ],
    "KeyE": [ "o", "O", "%" ],
    "KeyR": [ "w", "W", "!" ],
    "KeyT": [ "b", "B", "«", "“" ],
    "KeyY": [ "f", "F", "»", "”" ],
    "KeyU": [ "g", "G", "^", "€" ],
    "KeyI": [ "h", "H", "#", "£" ],
    "KeyO": [ "c", "C", "~", "≈" ],
    "KeyP": [ "x", "X", "*", "×" ],
    "KeyA": [ "a", "A", "<", "≤" ],
    "KeyS": [ "i", "I", ">", "≥" ],
    "KeyD": [ "e", "E", "{" ],
    "KeyF": [ "u", "U", "}" ],
    "KeyG": [ "k", "K", "\\" ],
    "KeyH": [ "v", "V", "|", "¦" ],
    "KeyJ": [ "s", "S", "(", "—" ],
    "KeyK": [ "n", "N", ")", "–" ],
    "KeyL": [ "t", "T", "[" ],
    "Semicolon": [ "r", "R", "]" ],
    "KeyZ": [ ".", ":", ":", "…" ],
    "KeyX": [ "j", "J", "/" ],
    "KeyC": [ "à", "À", "=" ],
    "KeyV": [ "**", "*¨", "\"" ],
    "KeyB": [ ",", ";", ";", "·" ],
    "KeyN": [ "m", "M", "&", "−" ],
    "KeyM": [ "d", "D", "$", "§" ],
    "Comma": [ "l", "L", "=", "≠" ],
    "Period": [ "p", "P", "+", "±" ],
    "Slash": [ "’", "?", "'", "¿" ],
    "Minus": [ "€", "€" ],
    "Equal": [ "%", "%" ],
    "BracketLeft": [ "[", "{" ],
    "BracketRight": [ "]", "}" ],
    "Quote": [ "'", "\"" ],
    "Backquote": [ "=", "+" ],
    "Backslash": [ "\\", "|" ],
    "IntlBackslash": [ "ê", "Ê" ],
    "Space": [ " ", "-", "_", " " ]
  },
  "deadkeys": {
    "**": { "**": "*¨", "0": "°", "Z": "Á", "z": "á", "Y": "Í", "y": "í", "O": "Ó", "o": "ó", "H": "Û", "h": "û", "C": "Ç", "c": "ç", "X": "Â", "x": "â", "A": "È", "a": "è", "I": "É", "i": "é", "E": "Œ", "e": "œ", "S": "Q", "s": "q", "N": "Ô", "n": "ô", ":": "Ù", ".": "ù", "J": "Æ", "j": "æ", "À": "Ê", "à": "ê", "M": "Ñ", "m": "ñ", "L": "Î", "l": "î", "’": "?", "ê": "^", "-": " ", " ": " ", " ": " " },
    "*¨": { "*¨": "¨", "A": "Ä", "a": "ä", "E": "Ë", "e": "ë", "H": "Ḧ", "h": "ḧ", "I": "Ï", "i": "ï", "O": "Ö", "o": "ö", "t": "ẗ", "U": "Ü", "u": "ü", "W": "Ẅ", "w": "ẅ", "X": "Ẍ", "x": "ẍ", "Y": "Ÿ", "y": "ÿ", " ": "\"", " ": "\"" }
  },
  "altgr": true
}